{"data":{"allMarkdownRemark":{"edges":[{"node":{"id":"52b8bf60-2969-5799-9c26-4f3c578042e5","frontmatter":{"path":"/qh15rvq7JVeTiksp2e8qKSsG","title":"结婚12年，让我受益的“9个基本”","date":"2018-11-19 14:17:00 +0800","auther":"宽宽"},"excerpt":"“婚姻会让人生更幸福”——这真是现实中最具杀伤力的谎言之一。文  |  宽宽 对于婚姻，我从来抱持着一种近乎悲观主义的态度。 谈恋爱时，从没想过一定要结婚，结婚后，从没期待能一起过多少年，更不曾痴想“执子之手与子偕老”的浪漫终老。 却一不小心，在一段关系中度过了1…"}},{"node":{"id":"da604cc0-bb1a-5db1-9d1b-e8317847e6f3","frontmatter":{"path":"/2N1lWmx8tQlaEPDQKX06Txib","title":"Github 静态站报 522 错误","date":"2018-09-27 10:29:00 +0800","auther":null},"excerpt":"发现自己的网站突然开始报 522 错误，之前查资料遇到过好多回，没想到这次轮到自己了。 错误做法 一开始以为是转载了些不和谐的文章被屏蔽了。 后来以为是阿里相应号召严格把控信息关，国外服务器不给解析过去了。 最后发现，其实是 github…"}},{"node":{"id":"9edbd6ae-c7c6-56c0-a6a6-d602cf0231b1","frontmatter":{"path":"/Z8r3O8d6bkxBF8XEKmBfqAIZ","title":"Sublime Text3 插件发布","date":"2018-02-07 22:10:00 +0800","auther":null},"excerpt":"注意，官方已经说明过，以前的发布方法不再适用，需要按以下的流程，才可以发布成功。 前言 之所以有这么多开发者使用Sublime Text来作为开发工具，归根到底是其有完善的生态系统。而Package Control…"}},{"node":{"id":"60a282ee-ab11-5076-a608-9d10cd9a7036","frontmatter":{"path":"/zZDqsfQ1PK8UNWIktSnZWnIF","title":"从零开始搭建 React 项目","date":"2018-02-07 21:08:25 +0800","auther":null},"excerpt":"# 搭建项目 # 创建页面 编辑  src/index.html 浏览器控制台看到日志输出。 # 引入 webpack 1. 初始化node环境 2. 引入webpack 编辑  webpack.config.js webpack 编译生成输出文件 修改  src/index…"}},{"node":{"id":"06ed83e9-d8ab-5c95-a3d0-c252a0e27f15","frontmatter":{"path":"/hqGjQ2JOSGwJk2jyLoDlHuvk","title":"中国人口流动的决定因素","date":"2017-12-04 14:53:12 +0800","auther":null},"excerpt":"…"}},{"node":{"id":"c5ce6312-0b9f-56ba-9ba3-a50fd066d216","frontmatter":{"path":"/Setu4UbkWfc2qskvni6WE9hY","title":"中国回到城乡隔离时代？","date":"2017-12-07 11:05:47 +0800","auther":null},"excerpt":"张千帆：按 “功能” 将各种城市和农村分为三六九等，经过计划年代的人应感觉似曾相识，本质上是新的城乡隔离。 近日，北京大兴一把大火不仅夺走了 1…"}},{"node":{"id":"0dcaa677-346d-5697-a386-15bfdbead949","frontmatter":{"path":"/OxeNGa1PLdmSDhQUCcxfmAR2","title":"最硬的招","date":"2017-12-04 15:19:12 +0800","auther":null},"excerpt":"…"}},{"node":{"id":"76022271-119e-5afc-bd2b-35470ecbd6ca","frontmatter":{"path":"/4rFXcuawHHvlOaY4CZ3EAnxx","title":"慈善组织花了那么多钱，为什么孩子还被虐待？","date":"2017-12-05 15:57:03 +0800","auther":null},"excerpt":"…"}},{"node":{"id":"e9681baa-58b1-5191-9070-a0f0c6263829","frontmatter":{"path":"/rRFgYArcukJMUYgYLGOKmuHC","title":"如何解开中日之间的心结？","date":"2017-12-12 11:49:26 +0800","auther":null},"excerpt":"…"}},{"node":{"id":"a646b734-95ce-5afe-ab58-19c35ee965ee","frontmatter":{"path":"/2XXJiI7mFTUSUSVlV4Y6EjOr","title":"公司衰败之根在于等级制度","date":"2017-12-18 18:01:20 +0800","auther":null},"excerpt":"…"}},{"node":{"id":"5ea3ed4f-bf4e-5294-aa32-05e040ae7d61","frontmatter":{"path":"/jcajHY2nug0xK7RxaaypAg7x","title":"用圣人标准衡量别人，用贱人标准要求自己","date":"2017-01-20 11:25:54 +0800","auther":null},"excerpt":"“现在人和人之间的矛盾，主要是来源于有那么一拨人，惯于用圣人的标准衡量别人，用贱人的标准要求自己。” 0…"}},{"node":{"id":"12d7b5a3-bdcb-55cf-af2f-6a665795507b","frontmatter":{"path":"/a3ZC4FuSzl15HCeXyylPNPPq","title":"我自横刀向天笑，笑完我就去睡觉","date":"2017-01-18 13:42:45 +0800","auther":null},"excerpt":"01 非常喜欢网络时代那些不靠谱的文字结构，\n总感觉在这种百分百恶搞的游戏之后，\n隐藏着点有可能会我们产生影响的东西。\n比如说这一句：\n 我自横刀向天笑，笑完我就去睡觉。 0…"}},{"node":{"id":"ccd01543-6451-5b48-8a5a-656be638577a","frontmatter":{"path":"/fmCbZ2i97uL3ESP2n8GLvpQo","title":"简单是最好的生存之道","date":"2017-01-18 14:22:53 +0800","auther":null},"excerpt":"“世界变得复杂，是因为你变得复杂。你简单了，世界就变得简单。”——百晓生 01 刘震云《一句顶一万句》讲了两个绝交故事：\n牛书道和冯世伦本是好朋友，\n两人说得上话，好了半辈子。\n入冬时节，他俩结伴去长治拉煤。\n那晚，离家还有2…"}},{"node":{"id":"c54d06ba-56e9-5f91-96b5-a35eab43587c","frontmatter":{"path":"/wijsxqhmT3Nt6yQEZJmzpeIy","title":"都市教养，是门槛最低的高贵","date":"2017-01-18 14:03:03 +0800","auther":null},"excerpt":"“都市是一种生活方式，它要求特定的教养。”学者汪丁丁说。\n“都市教养”是一种发自内心的温柔，一种以约束自己为前提的高贵，一种能设身处地为别人着想的善良。   01 1912年4月14日那个夜晚，\n泰坦尼克号撞上冰山而沉没。\n705人得救，150…"}},{"node":{"id":"ff566157-3f72-5f37-8a95-18ed52ab7094","frontmatter":{"path":"/v09WT4Hceb6VIeAyNx79WgiK","title":"为什么产品测试只找 5 位用户就够了？","date":"2017-01-25 15:08:07 +0800","auther":null},"excerpt":"有人认为可用性测试又烧钱又复杂，即使要用也应该是那一小部有预算、有时间的网页设计项目上面。但事实并非如此。复杂的可用性测试确实是种浪费。 其实，每次测试只需不超过五个用户。只要尽可能多搞些这种小测试，就能取得最佳效果。 在之前的研究中，Tom Landauer…"}}]}},"pageContext":{}}