{"data":{"markdownRemark":{"html":"<h4>前提条件：</h4>\n<p>JDK1.6 环境变量设置妥当</p>\n<p>工具JAR包：trang.jar\n下载地址：<a href=\"http://www.163disk.com/fileview_269095.html\">http://www.163disk.com/fileview_269095.html</a></p>\n<h4>步骤：</h4>\n<p>cmd进入xml所在目录，输入</p>\n<pre class=\"editor editor-colors\"><div class=\"line\"><span class=\"text plain null-grammar\"><span>java&nbsp;-jar&nbsp;trang.jar&nbsp;xxx.xml&nbsp;xxx.xsd</span></span></div></pre>\n<!--more-->\n<p>完成之后目录应该多出一个XSD文件。</p>\n<p>再输入</p>\n<pre class=\"editor editor-colors\"><div class=\"line\"><span class=\"text plain null-grammar\"><span>xjc&nbsp;-extension&nbsp;xxx.xsd</span></span></div></pre>\n<p>完成之后，会在所在目录的<code>generated</code>目录下生成一大堆java文件。\n其中<code>ObjectFactory.java</code>是工厂类。</p>\n<hr>","frontmatter":{"path":"/rC8fXtSV3TunDuJFk7KFMSX2","title":"XML生成Java类","date":"2011-10-21 15:50:09 +0800","comments":true,"categories":"programming","author":"Sir0xb","tags":["xml","java"]}}},"pageContext":{}}