{"data":{"markdownRemark":{"html":"<p><code>nginx.conf</code> 配置多个server属性即可，如下:</p>\n<pre><code class=\"language-xml\">... ...\nevents {\n    ... ...\n}\n... ...\nhttp {\n    i... ...\n    server {\n        ... ...\n    }\n\n    server {\n        ... ...\n    }\n\n    server {\n        ... ...\n    }\n\n    server {\n        ... ...\n    }\n\n    server {\n        listen       80;\n        server_name  Dojo;\n        charset utf-8;\n\n        location / {\n            root   WebServer/Dojo;\n\n            #开启目录浏览\n            autoindex on;\n        }\n    }\n}\n</code></pre>\n<p>注释：记得修改 <code>hosts</code> 文件，将 <code>server_name</code> 制定的域名，映射到 <code>127.0.0.1</code></p>\n<hr>","frontmatter":{"path":"/1i9hAd7YK2L0zPVsEi28nGD3","title":"Nginx配置虚拟服务器","date":"2011-12-26 09:15:57 +0800","comments":true,"categories":"programming","author":"Sir0xb","tags":["nginx"]}}},"pageContext":{}}